otio_aaf_adapter/__init__.py
otio_aaf_adapter/plugin_manifest.json
otio_aaf_adapter/adapters/__init__.py
otio_aaf_adapter/adapters/advanced_authoring_format.py
otio_aaf_adapter/adapters/aaf_adapter/__init__.py
otio_aaf_adapter/adapters/aaf_adapter/aaf_writer.py
otio_aaf_adapter-1.0.0.dist-info/LICENSE.txt
otio_aaf_adapter-1.0.0.dist-info/METADATA
otio_aaf_adapter-1.0.0.dist-info/WHEEL
otio_aaf_adapter-1.0.0.dist-info/entry_points.txt
otio_aaf_adapter-1.0.0.dist-info/top_level.txt
otio_aaf_adapter-1.0.0.dist-info/RECORD
