Metadata-Version: 2.1
Name: otio-aaf-adapter
Version: 1.0.0
Summary: OpenTimelineIO Advanced Authoring Format (AAF) Adapter
Home-page: https://github.com/markreidvfx/otio-aaf-adapter
Author: Contributors to the OpenTimelineIO project
Author-email: otio-discussion@lists.aswf.io
Platform: any
Classifier: Development Status :: 4 - Beta
Classifier: Intended Audience :: Developers
Classifier: Topic :: Multimedia :: Video
Classifier: Topic :: Multimedia :: Video :: Display
Classifier: Topic :: Multimedia :: Video :: Non-Linear Editor
Classifier: Topic :: Software Development :: Libraries :: Python Modules
Classifier: Programming Language :: Python :: 3
Classifier: Programming Language :: Python :: 3.7
Classifier: Programming Language :: Python :: 3.8
Classifier: Programming Language :: Python :: 3.9
Classifier: Programming Language :: Python :: 3.10
Classifier: Operating System :: OS Independent
Classifier: License :: OSI Approved :: Apache Software License
Classifier: Natural Language :: English
Requires-Python: >=3.7
Provides-Extra: dev
License-File: LICENSE.txt
